{
  "name": "calendar",
  "description": "A date calendar component for selecting dates.",
  "dependencies": ["@soybeanjs/headless", "@soybeanjs/cva", "@internationalized/date"],
  "registryDependencies": ["utils", "button"],
  "files": [
    {
      "path": "packages/ui/src/components/calendar/calendar.vue",
      "type": "registry:ui",
      "content": "<script setup lang=\"ts\" generic=\"M extends boolean = false\">\nimport { computed } from 'vue';\nimport { useLocaleMessages } from '@soybeanjs/headless';\nimport { CalendarCompact, provideCalendarUi } from '@soybeanjs/headless/calendar';\nimport { useForwardListeners, useOmitProps } from '@soybeanjs/headless/composables';\nimport { calendarVariants } from '@/styles/calendar';\nimport { miniSizeMap } from '@/theme';\nimport Icon from '../icon/icon.vue';\nimport SSelect from '../select/select.vue';\nimport type { CalendarProps, CalendarEmits, CalendarSlots } from './types';\n\ndefineOptions({\n  name: 'SCalendar'\n});\n\nconst props = defineProps<CalendarProps<M>>();\n\nconst emit = defineEmits<CalendarEmits<M>>();\n\ndefineSlots<CalendarSlots<M>>();\n\nconst forwardedProps = useOmitProps(props, ['class', 'size', 'ui']);\n\nconst listeners = useForwardListeners(emit);\n\nconst messages = useLocaleMessages();\n\nconst monthTriggerProps = computed(() => ({ 'aria-label': messages.value.calendar.selectMonth }));\n\nconst yearTriggerProps = computed(() => ({ 'aria-label': messages.value.calendar.selectYear }));\n\nconst ui = computed(() => calendarVariants({ size: props.size }, props.ui, { root: props.class }));\n\nconst miniSize = computed(() => miniSizeMap[props.size || 'md']);\n\nprovideCalendarUi(ui);\n</script>\n\n<template>\n  <CalendarCompact v-bind=\"forwardedProps\" v-on=\"listeners\">\n    <template #prev=\"slotProps\">\n      <slot name=\"prev\" v-bind=\"slotProps\">\n        <Icon icon=\"lucide:chevron-left\" />\n      </slot>\n    </template>\n    <template v-if=\"$slots.heading\" #heading=\"slotProps\">\n      <slot name=\"heading\" v-bind=\"slotProps\" />\n    </template>\n    <template v-else #heading=\"{ monthOptions, yearOptions, selectedMonth, selectedYear, onMonthChange, onYearChange }\">\n      <SSelect\n        :size=\"miniSize\"\n        :disabled=\"disabled\"\n        :clearable=\"false\"\n        :items=\"monthOptions\"\n        :model-value=\"selectedMonth\"\n        :trigger-props=\"monthTriggerProps\"\n        :ui=\"{ trigger: 'w-fit' }\"\n        @update:model-value=\"onMonthChange\"\n      />\n      <SSelect\n        :size=\"miniSize\"\n        :disabled=\"disabled\"\n        :clearable=\"false\"\n        :items=\"yearOptions\"\n        :model-value=\"selectedYear\"\n        :trigger-props=\"yearTriggerProps\"\n        :ui=\"{ popup: 'max-h-72', trigger: 'w-fit' }\"\n        @update:model-value=\"onYearChange\"\n      />\n    </template>\n    <template #next=\"slotProps\">\n      <slot name=\"next\" v-bind=\"slotProps\">\n        <Icon icon=\"lucide:chevron-right\" />\n      </slot>\n    </template>\n    <template #head-cell=\"slotProps\">\n      <slot name=\"head-cell\" v-bind=\"slotProps\">\n        {{ slotProps.label }}\n      </slot>\n    </template>\n    <template #day=\"slotProps\">\n      <slot name=\"day\" v-bind=\"slotProps\">\n        {{ slotProps.dayValue }}\n      </slot>\n    </template>\n    <template #default=\"slotProps\">\n      <slot v-bind=\"slotProps\" />\n    </template>\n  </CalendarCompact>\n</template>\n"
    },
    {
      "path": "packages/ui/src/components/calendar/types.ts",
      "type": "registry:lib",
      "content": "import type {\n  CalendarCompactProps,\n  CalendarCompactEmits,\n  CalendarCompactSlots,\n  CalendarUi\n} from '@soybeanjs/headless/calendar';\nimport type { ClassValue } from '@soybeanjs/headless/types';\nimport type { ThemeSize } from '@/theme';\n\n/**\n * Properties for the Calendar component.\n */\nexport interface CalendarProps<M extends boolean = false> extends CalendarCompactProps<M> {\n  /**\n   * Additional class names applied to the root element.\n   */\n  class?: ClassValue;\n  /**\n   * Visual size of the component.\n   */\n  size?: ThemeSize;\n  /**\n   * Per-slot class overrides for the component.\n   */\n  ui?: Partial<CalendarUi>;\n}\n\n/**\n * Events for the Calendar component.\n */\nexport type CalendarEmits<M extends boolean = false> = CalendarCompactEmits<M>;\n\n/**\n * Slots for the Calendar component.\n */\nexport type CalendarSlots<M extends boolean = false> = CalendarCompactSlots<M>;\n"
    },
    {
      "path": "packages/ui/src/styles/calendar.ts",
      "type": "registry:style",
      "content": "// @unocss-include\nimport { scv } from '@soybeanjs/cva';\nimport { miniButtonIconVariants } from './button';\n\nexport const calendarVariants = scv({\n  extendBase: props => ({\n    prev: miniButtonIconVariants({\n      size: props.size,\n      variant: 'pure'\n    }),\n    next: miniButtonIconVariants({\n      size: props.size,\n      variant: 'pure'\n    })\n  }),\n  slots: {\n    root: 'inline-flex flex-col rounded-md border shadow-sm',\n    header: 'flex items-center justify-between',\n    heading: 'flex items-center justify-center font-medium',\n    prev: 'rtl:rotate-180',\n    next: 'rtl:rotate-180',\n    grid: 'inline-table border-collapse',\n    gridHead: '',\n    gridBody: '',\n    gridRow: '',\n    headCell: 'rounded-md text-center font-normal text-muted-foreground',\n    cell: [\n      'flex-1 text-center align-middle',\n      'focus-within:relative focus-within:z-20 [&:has([data-selected])]:rounded-md [&:has([data-selected])]:bg-accent'\n    ],\n    cellTrigger: [\n      'inline-flex items-center justify-center w-full h-full rounded-md transition-colors cursor-pointer',\n      'outline-none focus-visible:ring-3 focus-visible:ring-offset-background focus-visible:ring-ring focus-visible:ring-primary/30',\n      'data-[selected]:bg-primary data-[selected]:text-primary-foreground data-[selected]:font-medium',\n      '[&:not([data-selected]):hover]:bg-accent [&:not([data-selected]):hover]:text-accent-foreground',\n      'data-[disabled]:cursor-not-allowed data-[disabled]:text-muted-foreground data-[disabled]:opacity-50',\n      '[&[data-today]:not([data-selected])]:bg-accent [&[data-today]:not([data-selected])]:text-accent-foreground',\n      'data-[unavailable]:line-through data-[outside-view]:text-muted-foreground'\n    ]\n  },\n  variants: {\n    size: {\n      xs: {\n        root: 'gap-3 text-2xs p-2',\n        header: 'gap-1.5',\n        gridRow: 'mt-1.5',\n        heading: 'gap-1.5',\n        headCell: 'h-6 w-6 text-3xs',\n        cell: 'h-6 w-6'\n      },\n      sm: {\n        root: 'gap-3.5 text-xs p-2.5',\n        header: 'gap-2',\n        gridRow: 'mt-1.75',\n        heading: 'gap-2',\n        headCell: 'h-7 w-7 text-2xs',\n        cell: 'h-7 w-7'\n      },\n      md: {\n        root: 'gap-4 text-sm p-3',\n        header: 'gap-2.5',\n        gridRow: 'mt-2',\n        heading: 'gap-2.5',\n        headCell: 'h-8 w-8 text-xs',\n        cell: 'h-8 w-8'\n      },\n      lg: {\n        root: 'gap-4.5 text-base p-3.5',\n        header: 'gap-3',\n        gridRow: 'mt-2.25',\n        heading: 'gap-3',\n        headCell: 'h-9 w-9 text-sm',\n        cell: 'h-9 w-9'\n      },\n      xl: {\n        root: 'gap-5 text-lg p-4',\n        header: 'gap-3.5',\n        gridRow: 'mt-2.5',\n        heading: 'gap-3.5',\n        headCell: 'h-10 w-10 text-base',\n        cell: 'h-10 w-10'\n      },\n      '2xl': {\n        root: 'gap-6 text-xl p-5',\n        header: 'gap-4',\n        gridRow: 'mt-3',\n        heading: 'gap-4',\n        headCell: 'h-12 w-12 text-lg',\n        cell: 'h-12 w-12'\n      }\n    }\n  },\n  defaultVariants: {\n    size: 'md'\n  }\n});\n"
    }
  ],
  "categories": ["form", "date"],
  "type": "registry:ui"
}
